Metadata-Version: 1.0
Name: sxysp
Version: 0.1
Summary: SXYSP Cli Toolbox
Home-page: https://github.com/xxx
Author: sunxyw
Author-email: xy2496419818@gmail.com
License: MIT
Keywords: sxysp
Platform: UNKNOWN
